notes_compiler/__init__.py
notes_compiler/config.py
notes_compiler/html_page.py
notes_compiler/main.py
notes_compiler/resources/__init__.py
notes_compiler/resources/header.css
notes_compiler/tree_node.py
notes_compiler/utils.py
notes_compiler-0.3.3.dist-info/entry_points.txt
notes_compiler-0.3.3.dist-info/WHEEL
notes_compiler-0.3.3.dist-info/METADATA
notes_compiler-0.3.3.dist-info/RECORD
